odoo/addons/pos_event_sale/README.rst
odoo/addons/pos_event_sale/__init__.py
odoo/addons/pos_event_sale/__manifest__.py
odoo/addons/pos_event_sale/i18n/pos_event_sale.pot
odoo/addons/pos_event_sale/models/__init__.py
odoo/addons/pos_event_sale/models/event_registration.py
odoo/addons/pos_event_sale/models/pos_config.py
odoo/addons/pos_event_sale/models/pos_order.py
odoo/addons/pos_event_sale/models/pos_order_line.py
odoo/addons/pos_event_sale/readme/CONFIGURE.rst
odoo/addons/pos_event_sale/readme/CONTRIBUTORS.rst
odoo/addons/pos_event_sale/readme/DESCRIPTION.rst
odoo/addons/pos_event_sale/readme/ROADMAP.rst
odoo/addons/pos_event_sale/readme/USAGE.rst
odoo/addons/pos_event_sale/report/__init__.py
odoo/addons/pos_event_sale/report/pos_order_report.py
odoo/addons/pos_event_sale/security/security.xml
odoo/addons/pos_event_sale/static/description/add_event_button.png
odoo/addons/pos_event_sale/static/description/event_calendar.png
odoo/addons/pos_event_sale/static/description/icon.png
odoo/addons/pos_event_sale/static/description/index.html
odoo/addons/pos_event_sale/static/description/ticket_selector.png
odoo/addons/pos_event_sale/static/src/css/pos_event_sale.scss
odoo/addons/pos_event_sale/static/src/js/db.js
odoo/addons/pos_event_sale/static/src/js/models.js
odoo/addons/pos_event_sale/static/src/js/screens.js
odoo/addons/pos_event_sale/static/src/js/models/Order.js
odoo/addons/pos_event_sale/static/src/js/models/Orderline.js
odoo/addons/pos_event_sale/static/src/js/models/PosModel.js
odoo/addons/pos_event_sale/static/src/js/popups/EventSelectorPopup.js
odoo/addons/pos_event_sale/static/src/js/popups/EventTicketsPopup.js
odoo/addons/pos_event_sale/static/src/js/tours/TourBasic.js
odoo/addons/pos_event_sale/static/src/js/tours/tour.utils.js
odoo/addons/pos_event_sale/static/src/xml/EventSelectorPopup.xml
odoo/addons/pos_event_sale/static/src/xml/EventTicketsPopup.xml
odoo/addons/pos_event_sale/static/src/xml/popups.xml
odoo/addons/pos_event_sale/static/src/xml/pos.xml
odoo13_addon_pos_event_sale-13.0.1.0.1.dist-info/METADATA
odoo13_addon_pos_event_sale-13.0.1.0.1.dist-info/WHEEL
odoo13_addon_pos_event_sale-13.0.1.0.1.dist-info/top_level.txt
odoo13_addon_pos_event_sale-13.0.1.0.1.dist-info/RECORD
